twitter_fire_scraper/__init__.py
twitter_fire_scraper/app.py
twitter_fire_scraper/config.py
twitter_fire_scraper/hashtags.py
twitter_fire_scraper/models.py
twitter_fire_scraper/scraper.py
twitter_fire_scraper/text_classifier.py
twitter_fire_scraper/twitter.py
twitter_fire_scraper/util.py
twitter_fire_scraper/data/AccountsFireNotifiersChicago.yml
twitter_fire_scraper/data/DisasterHashtags.yml
twitter_fire_scraper/data/FireHashtags.yml
twitter_fire_scraper/data/FloodHashtags.yml
twitter_fire_scraper/data/MajorCities.yml
twitter_fire_scraper/data/TwitterAccounts.yml
twitter_fire_scraper/data/USStates.yml
twitter_fire_scraper/database/PasswordUtils.py
twitter_fire_scraper/database/StatusUtils.py
twitter_fire_scraper/database/TweetResult.py
twitter_fire_scraper/database/TweetResultDAO.py
twitter_fire_scraper/database/User.py
twitter_fire_scraper/database/__init__.py
twitter_fire_scraper/flask_app/__init__.py
twitter_fire_scraper/flask_app/app.py
twitter_fire_scraper/flask_app/forms.py
twitter_fire_scraper/flask_app/http_api.py
twitter_fire_scraper/flask_app/http_forms.py
twitter_fire_scraper/tests/__init__.py
twitter_fire_scraper/tests/interactive/__init__.py
twitter_fire_scraper/tests/interactive/testAllTwitterFire.py
twitter_fire_scraper/tests/interactive/testListenGeoFires.py
twitter_fire_scraper/tests/interactive/testListenGeoFiresMongoDB.py
twitter_fire_scraper/tests/interactive/testScrapeChicagoFireHashtags.py
twitter_fire_scraper/tests/interactive/testScraperSimpleAccounts.py
twitter_fire_scraper/tests/interactive/testScraperSimpleTermsPizza.py
twitter_fire_scraper/tests/test/__init__.py
twitter_fire_scraper/tests/test/__main__.py
twitter_fire_scraper/tests/test/testFileSaving.py
twitter_fire_scraper/tests/test/testGeolib.py
twitter_fire_scraper/tests/test/testHashtag.py
twitter_fire_scraper/tests/test/testScraperInvalidCredentials.py
twitter_fire_scraper/tests/test/testUtil.py
twitter_fire_scraper/tests/test/dao/__init__.py
twitter_fire_scraper-2.2.0.dist-info/METADATA
twitter_fire_scraper-2.2.0.dist-info/WHEEL
twitter_fire_scraper-2.2.0.dist-info/top_level.txt
twitter_fire_scraper-2.2.0.dist-info/RECORD
