Metadata-Version: 2.1
Name: twitter-fire-scraper
Version: 2.2.0
Summary: A tool to scrape data about fires from Twitter.
Home-page: https://github.com/twitter-fire-scraper-analytics/twitter-fire-scraper
Author: Henry Post
Author-email: HenryFBP@gmail.com
License: UNKNOWN
Platform: UNKNOWN
Classifier: Programming Language :: Python :: 3
Classifier: License :: OSI Approved :: GNU General Public License v3 or later (GPLv3+)
Classifier: Operating System :: OS Independent
Requires-Dist: Flask
Requires-Dist: Jinja2
Requires-Dist: MarkupSafe
Requires-Dist: Werkzeug
Requires-Dist: certifi
Requires-Dist: chardet
Requires-Dist: click
Requires-Dist: colorama
Requires-Dist: dnspython
Requires-Dist: flask-bootstrap4
Requires-Dist: flask-login
Requires-Dist: flask-pymongo
Requires-Dist: itsdangerous
Requires-Dist: matplotlib
Requires-Dist: nltk
Requires-Dist: numpy
Requires-Dist: oauthlib
Requires-Dist: pymongo
Requires-Dist: pyyaml
Requires-Dist: requests
Requires-Dist: requests-oauthlib
Requires-Dist: six
Requires-Dist: textblob
Requires-Dist: tmdbsimple
Requires-Dist: tweepy
Requires-Dist: typing
